cryptography_vectors/__about__.py
cryptography_vectors/__init__.py
cryptography_vectors/asymmetric/DH/KASValidityTest_FFCStatic_NOKC_ZZOnly_init.fax
cryptography_vectors/asymmetric/DH/KASValidityTest_FFCStatic_NOKC_ZZOnly_resp.fax
cryptography_vectors/asymmetric/DSA/FIPS_186-2/KeyPair.rsp
cryptography_vectors/asymmetric/DSA/FIPS_186-2/PQGGen.rsp
cryptography_vectors/asymmetric/DSA/FIPS_186-2/PQGGen.txt
cryptography_vectors/asymmetric/DSA/FIPS_186-2/PQGVer.rsp
cryptography_vectors/asymmetric/DSA/FIPS_186-2/Readme.txt
cryptography_vectors/asymmetric/DSA/FIPS_186-2/SigGen.rsp
cryptography_vectors/asymmetric/DSA/FIPS_186-2/SigGen.txt
cryptography_vectors/asymmetric/DSA/FIPS_186-2/SigVer.rsp
cryptography_vectors/asymmetric/DSA/FIPS_186-3/KeyPair.rsp
cryptography_vectors/asymmetric/DSA/FIPS_186-3/PQGGen.rsp
cryptography_vectors/asymmetric/DSA/FIPS_186-3/PQGGen.txt
cryptography_vectors/asymmetric/DSA/FIPS_186-3/PQGVer.rsp
cryptography_vectors/asymmetric/DSA/FIPS_186-3/Readme.txt
cryptography_vectors/asymmetric/DSA/FIPS_186-3/SigGen.rsp
cryptography_vectors/asymmetric/DSA/FIPS_186-3/SigGen.txt
cryptography_vectors/asymmetric/DSA/FIPS_186-3/SigVer.rsp
cryptography_vectors/asymmetric/ECDH/KASValidityTest_ECCStaticUnified_NOKC_ZZOnly_init.fax
cryptography_vectors/asymmetric/ECDH/KASValidityTest_ECCStaticUnified_NOKC_ZZOnly_resp.fax
cryptography_vectors/asymmetric/ECDSA/FIPS_186-2/KeyPair.rsp
cryptography_vectors/asymmetric/ECDSA/FIPS_186-2/PKV.rsp
cryptography_vectors/asymmetric/ECDSA/FIPS_186-2/Readme.txt
cryptography_vectors/asymmetric/ECDSA/FIPS_186-2/SigGen.rsp
cryptography_vectors/asymmetric/ECDSA/FIPS_186-2/SigGen.txt
cryptography_vectors/asymmetric/ECDSA/FIPS_186-2/SigVer.rsp
cryptography_vectors/asymmetric/ECDSA/FIPS_186-3/KeyPair.rsp
cryptography_vectors/asymmetric/ECDSA/FIPS_186-3/PKV.rsp
cryptography_vectors/asymmetric/ECDSA/FIPS_186-3/Readme.txt
cryptography_vectors/asymmetric/ECDSA/FIPS_186-3/SigGen.rsp
cryptography_vectors-0.6.1.dist-info/DESCRIPTION.rst
cryptography_vectors-0.6.1.dist-info/METADATA
cryptography_vectors-0.6.1.dist-info/pydist.json
cryptography_vectors-0.6.1.dist-info/RECORD
cryptography_vectors-0.6.1.dist-info/top_level.txt
cryptography_vectors-0.6.1.dist-info/WHEEL
