Metadata-Version: 2.0
Name: cryptography-vectors
Version: 0.6.1
Summary: Test vectors for the cryptography package.
Home-page: https://github.com/pyca/cryptography
Author: The cryptography developers
Author-email: cryptography-dev@python.org
License: Apache License, Version 2.0
Platform: UNKNOWN
